README.txt
setup.cfg
setup.py
docs/HISTORY.txt
docs/INSTALL.txt
docs/LICENSE.GPL
docs/LICENSE.txt
easyshop/__init__.py
easyshop.search.egg-info/PKG-INFO
easyshop.search.egg-info/SOURCES.txt
easyshop.search.egg-info/dependency_links.txt
easyshop.search.egg-info/entry_points.txt
easyshop.search.egg-info/namespace_packages.txt
easyshop.search.egg-info/not-zip-safe
easyshop.search.egg-info/requires.txt
easyshop.search.egg-info/top_level.txt
easyshop/search/__init__.py
easyshop/search/configure.zcml
easyshop/search/overrides.zcml
easyshop/search/profiles.zcml
easyshop/search/tests.py
easyshop/search/browser/__init__.py
easyshop/search/browser/configure.zcml
easyshop/search/browser/search.pt
easyshop/search/browser/search.py
easyshop/search/content/__init__.py
easyshop/search/content/container.py
easyshop/search/portlets/__init__.py
easyshop/search/portlets/configure.zcml
easyshop/search/portlets/search_results.pt
easyshop/search/portlets/search_results.py
easyshop/search/profiles/__init__.py
easyshop/search/profiles/default/portlets.xml
easyshop/search/profiles/default/propertiestool.xml
easyshop/search/profiles/default/skins.xml
easyshop/search/profiles/default/types.xml
easyshop/search/profiles/default/workflows.xml
easyshop/search/profiles/default/types/SearchResultContainer.xml
easyshop/search/skins/easyshop_search/livesearch_reply.py
easyshop/search/viewlets/__init__.py
easyshop/search/viewlets/configure.zcml
easyshop/search/viewlets/interfaces.py
easyshop/search/viewlets/overrides.zcml
easyshop/search/viewlets/search_results.pt
easyshop/search/viewlets/search_results.py
easyshop/search/viewlets/searchbox.pt
easyshop/search/viewlets/searchbox.py