Metadata-Version: 1.0
Name: easyshop.search
Version: 0.1a1
Summary: Search replacement for EasyShop
Home-page: http://iqpp.de
Author: Kai Diefenbach
Author-email: kai.diefenbach@iqpp.de
License: GPL
Keywords: plone search e-commerce online-shop
Platform: UNKNOWN
Classifier: Framework :: Plone
Classifier: Framework :: Zope2
Classifier: Framework :: Zope3
Classifier: Programming Language :: Python
Classifier: Topic :: Software Development :: Libraries :: Python Modules
